<?xml version="1.0" encoding="UTF-8"?>
<!DOCTYPE mapper PUBLIC "-//mybatis.org//DTD Mapper 3.0//EN" "http://mybatis.org/dtd/mybatis-3-mapper.dtd">
<mapper namespace="com.syscom.fep.mybatis.mapper.AtmtroutdataMapper">
  <resultMap id="BaseResultMap" type="com.syscom.fep.mybatis.model.Atmtroutdata">
    <!--
      WARNING - @mbg.generated
      This element is automatically generated by MyBatis Generator, do not modify.
    -->
    <constructor>
      <idArg column="TXDATE" javaType="java.lang.String" jdbcType="VARCHAR" />
      <idArg column="HOUR" javaType="java.lang.String" jdbcType="VARCHAR" />
      <idArg column="NUM" javaType="java.lang.Integer" jdbcType="INTEGER" />
      <arg column="FLOW" javaType="java.lang.String" jdbcType="VARCHAR" />
      <arg column="CHANNEL_TYPE" javaType="java.lang.String" jdbcType="VARCHAR" />
      <arg column="CHANNEL" javaType="java.lang.String" jdbcType="VARCHAR" />
      <arg column="KIND" javaType="java.lang.String" jdbcType="VARCHAR" />
      <arg column="CNT" javaType="java.lang.Integer" jdbcType="INTEGER" />
      <arg column="AMT" javaType="java.math.BigDecimal" jdbcType="DECIMAL" />
    </constructor>
  </resultMap>
  <sql id="Base_Column_List">
    <!--
      WARNING - @mbg.generated
      This element is automatically generated by MyBatis Generator, do not modify.
    -->
    TXDATE, HOUR, NUM, FLOW, CHANNEL_TYPE, CHANNEL, KIND, CNT, AMT
  </sql>
  <select id="selectByPrimaryKey" parameterType="map" resultMap="BaseResultMap">
    <!--
      WARNING - @mbg.generated
      This element is automatically generated by MyBatis Generator, do not modify.
    -->
    select 
    <include refid="Base_Column_List" />
    from ATMTROUTDATA
    where TXDATE = #{txdate,jdbcType=VARCHAR}
      and HOUR = #{hour,jdbcType=VARCHAR}
      and NUM = #{num,jdbcType=INTEGER}
  </select>
  <delete id="deleteByPrimaryKey" parameterType="com.syscom.fep.mybatis.model.Atmtroutdata">
    <!--
      WARNING - @mbg.generated
      This element is automatically generated by MyBatis Generator, do not modify.
    -->
    delete from ATMTROUTDATA
    where TXDATE = #{txdate,jdbcType=VARCHAR}
      and HOUR = #{hour,jdbcType=VARCHAR}
      and NUM = #{num,jdbcType=INTEGER}
  </delete>
  <insert id="insert" parameterType="com.syscom.fep.mybatis.model.Atmtroutdata">
    <!--
      WARNING - @mbg.generated
      This element is automatically generated by MyBatis Generator, do not modify.
    -->
    insert into ATMTROUTDATA (TXDATE, HOUR, NUM, 
      FLOW, CHANNEL_TYPE, CHANNEL, 
      KIND, CNT, AMT)
    values (#{txdate,jdbcType=VARCHAR}, #{hour,jdbcType=VARCHAR}, #{num,jdbcType=INTEGER}, 
      #{flow,jdbcType=VARCHAR}, #{channelType,jdbcType=VARCHAR}, #{channel,jdbcType=VARCHAR}, 
      #{kind,jdbcType=VARCHAR}, #{cnt,jdbcType=INTEGER}, #{amt,jdbcType=DECIMAL})
  </insert>
  <insert id="insertSelective" parameterType="com.syscom.fep.mybatis.model.Atmtroutdata">
    <!--
      WARNING - @mbg.generated
      This element is automatically generated by MyBatis Generator, do not modify.
    -->
    insert into ATMTROUTDATA
    <trim prefix="(" suffix=")" suffixOverrides=",">
      <if test="txdate != null">
        TXDATE,
      </if>
      <if test="hour != null">
        HOUR,
      </if>
      <if test="num != null">
        NUM,
      </if>
      <if test="flow != null">
        FLOW,
      </if>
      <if test="channelType != null">
        CHANNEL_TYPE,
      </if>
      <if test="channel != null">
        CHANNEL,
      </if>
      <if test="kind != null">
        KIND,
      </if>
      <if test="cnt != null">
        CNT,
      </if>
      <if test="amt != null">
        AMT,
      </if>
    </trim>
    <trim prefix="values (" suffix=")" suffixOverrides=",">
      <if test="txdate != null">
        #{txdate,jdbcType=VARCHAR},
      </if>
      <if test="hour != null">
        #{hour,jdbcType=VARCHAR},
      </if>
      <if test="num != null">
        #{num,jdbcType=INTEGER},
      </if>
      <if test="flow != null">
        #{flow,jdbcType=VARCHAR},
      </if>
      <if test="channelType != null">
        #{channelType,jdbcType=VARCHAR},
      </if>
      <if test="channel != null">
        #{channel,jdbcType=VARCHAR},
      </if>
      <if test="kind != null">
        #{kind,jdbcType=VARCHAR},
      </if>
      <if test="cnt != null">
        #{cnt,jdbcType=INTEGER},
      </if>
      <if test="amt != null">
        #{amt,jdbcType=DECIMAL},
      </if>
    </trim>
  </insert>
  <update id="updateByPrimaryKeySelective" parameterType="com.syscom.fep.mybatis.model.Atmtroutdata">
    <!--
      WARNING - @mbg.generated
      This element is automatically generated by MyBatis Generator, do not modify.
    -->
    update ATMTROUTDATA
    <set>
      <if test="flow != null">
        FLOW = #{flow,jdbcType=VARCHAR},
      </if>
      <if test="channelType != null">
        CHANNEL_TYPE = #{channelType,jdbcType=VARCHAR},
      </if>
      <if test="channel != null">
        CHANNEL = #{channel,jdbcType=VARCHAR},
      </if>
      <if test="kind != null">
        KIND = #{kind,jdbcType=VARCHAR},
      </if>
      <if test="cnt != null">
        CNT = #{cnt,jdbcType=INTEGER},
      </if>
      <if test="amt != null">
        AMT = #{amt,jdbcType=DECIMAL},
      </if>
    </set>
    where TXDATE = #{txdate,jdbcType=VARCHAR}
      and HOUR = #{hour,jdbcType=VARCHAR}
      and NUM = #{num,jdbcType=INTEGER}
  </update>
  <update id="updateByPrimaryKey" parameterType="com.syscom.fep.mybatis.model.Atmtroutdata">
    <!--
      WARNING - @mbg.generated
      This element is automatically generated by MyBatis Generator, do not modify.
    -->
    update ATMTROUTDATA
    set FLOW = #{flow,jdbcType=VARCHAR},
      CHANNEL_TYPE = #{channelType,jdbcType=VARCHAR},
      CHANNEL = #{channel,jdbcType=VARCHAR},
      KIND = #{kind,jdbcType=VARCHAR},
      CNT = #{cnt,jdbcType=INTEGER},
      AMT = #{amt,jdbcType=DECIMAL}
    where TXDATE = #{txdate,jdbcType=VARCHAR}
      and HOUR = #{hour,jdbcType=VARCHAR}
      and NUM = #{num,jdbcType=INTEGER}
  </update>
</mapper>