<?xml version="1.0" encoding="UTF-8"?>
<!DOCTYPE mapper PUBLIC "-//mybatis.org//DTD Mapper 3.0//EN" "http://mybatis.org/dtd/mybatis-3-mapper.dtd">
<mapper namespace="com.syscom.fep.mybatis.mapper.CardnotsmMapper">
  <resultMap id="BaseResultMap" type="com.syscom.fep.mybatis.model.Cardnotsm">
    <!--
      WARNING - @mbg.generated
      This element is automatically generated by MyBatis Generator, do not modify.
    -->
    <constructor>
      <idArg column="CARDNO" javaType="java.lang.String" jdbcType="CHAR" />
      <arg column="ACTNO" javaType="java.lang.String" jdbcType="CHAR" />
      <arg column="CARD_SEQ" javaType="java.lang.Short" jdbcType="DECIMAL" />
      <arg column="PRODTYPE" javaType="java.lang.Short" jdbcType="DECIMAL" />
      <arg column="CARDKIND" javaType="java.lang.Short" jdbcType="DECIMAL" />
      <arg column="CARDTYPE" javaType="java.lang.Short" jdbcType="DECIMAL" />
      <arg column="ISPRINTACTNO" javaType="java.lang.Short" jdbcType="SMALLINT" />
      <arg column="PRINTACTNO" javaType="java.lang.String" jdbcType="VARCHAR" />
      <arg column="MAKEDATE" javaType="java.lang.String" jdbcType="CHAR" />
      <arg column="IDNO1" javaType="java.lang.String" jdbcType="CHAR" />
      <arg column="IDNO2" javaType="java.lang.String" jdbcType="CHAR" />
      <arg column="PIDNO1" javaType="java.lang.String" jdbcType="VARCHAR" />
      <arg column="PIDERR" javaType="java.lang.String" jdbcType="CHAR" />
      <arg column="PIDNAT" javaType="java.lang.String" jdbcType="CHAR" />
      <arg column="TCARD" javaType="java.lang.Short" jdbcType="DECIMAL" />
      <arg column="LETTER" javaType="java.lang.String" jdbcType="CHAR" />
      <arg column="APPKIND" javaType="java.lang.Short" jdbcType="DECIMAL" />
      <arg column="BIRTHDAY" javaType="java.lang.String" jdbcType="VARCHAR" />
      <arg column="OFFSET" javaType="java.lang.Integer" jdbcType="INTEGER" />
      <arg column="STATUS" javaType="java.lang.Short" jdbcType="DECIMAL" />
      <arg column="PRESTATUS" javaType="java.lang.Short" jdbcType="DECIMAL" />
      <arg column="APDATE" javaType="java.lang.String" jdbcType="CHAR" />
      <arg column="APPLY_EJFNO" javaType="java.lang.Integer" jdbcType="INTEGER" />
      <arg column="BUSINO" javaType="java.lang.String" jdbcType="VARCHAR" />
      <arg column="DEPID" javaType="java.lang.String" jdbcType="CHAR" />
      <arg column="EMPNO" javaType="java.lang.String" jdbcType="VARCHAR" />
      <arg column="CNAME" javaType="java.lang.String" jdbcType="VARCHAR" />
      <arg column="COMPANY" javaType="java.lang.String" jdbcType="VARCHAR" />
      <arg column="DEPNAME" javaType="java.lang.String" jdbcType="VARCHAR" />
      <arg column="APBRNO" javaType="java.lang.String" jdbcType="CHAR" />
      <arg column="TERMID" javaType="java.lang.String" jdbcType="CHAR" />
      <arg column="APUSERID" javaType="java.lang.String" jdbcType="CHAR" />
      <arg column="SIGNID" javaType="java.lang.String" jdbcType="CHAR" />
      <arg column="ICPU" javaType="java.lang.Short" jdbcType="DECIMAL" />
      <arg column="APPGP" javaType="java.lang.String" jdbcType="CHAR" />
      <arg column="SELF" javaType="java.lang.String" jdbcType="CHAR" />
      <arg column="APPTFR" javaType="java.lang.Short" jdbcType="DECIMAL" />
      <arg column="PRINT_PASS" javaType="java.lang.Short" jdbcType="DECIMAL" />
      <arg column="BRNO" javaType="java.lang.String" jdbcType="CHAR" />
      <arg column="CHIPID" javaType="java.lang.String" jdbcType="CHAR" />
      <arg column="SIGNDATE" javaType="java.lang.String" jdbcType="CHAR" />
      <arg column="PRINTDATE" javaType="java.lang.String" jdbcType="CHAR" />
      <arg column="EMERGENCY" javaType="java.lang.Short" jdbcType="SMALLINT" />
      <arg column="UPDATE_USERID" javaType="java.lang.Integer" jdbcType="INTEGER" />
      <arg column="UPDATE_TIME" javaType="java.util.Date" jdbcType="TIMESTAMP" />
      <arg column="CREDITNO" javaType="java.lang.String" jdbcType="VARCHAR" />
      <arg column="DEBITNO" javaType="java.lang.String" jdbcType="VARCHAR" />
      <arg column="EASYNO" javaType="java.lang.String" jdbcType="VARCHAR" />
      <arg column="CUPNO" javaType="java.lang.String" jdbcType="VARCHAR" />
      <arg column="CREDITEXDATE" javaType="java.lang.String" jdbcType="VARCHAR" />
      <arg column="DEBITEXDATE" javaType="java.lang.String" jdbcType="VARCHAR" />
      <arg column="EASYEXDATE" javaType="java.lang.String" jdbcType="VARCHAR" />
      <arg column="CUPEXDATE" javaType="java.lang.String" jdbcType="VARCHAR" />
      <arg column="EASYCHIPID" javaType="java.lang.String" jdbcType="VARCHAR" />
      <arg column="ISAMCHIPSEQNO" javaType="java.lang.String" jdbcType="VARCHAR" />
      <arg column="ISAMBATCHNO" javaType="java.lang.String" jdbcType="VARCHAR" />
      <arg column="ISAMMAKESEQNO" javaType="java.lang.String" jdbcType="VARCHAR" />
      <arg column="MAKECARDRESULT" javaType="java.lang.String" jdbcType="VARCHAR" />
      <arg column="MAKECARDREMARK" javaType="java.lang.String" jdbcType="VARCHAR" />
      <arg column="MAKECARDTYPE" javaType="java.lang.String" jdbcType="VARCHAR" />
      <arg column="SALEMARK" javaType="java.lang.String" jdbcType="VARCHAR" />
      <arg column="MAKECARDRESDATE" javaType="java.lang.String" jdbcType="VARCHAR" />
      <arg column="SEID" javaType="java.lang.String" jdbcType="VARCHAR" />
      <arg column="PAYMENTSCHEME" javaType="java.lang.String" jdbcType="VARCHAR" />
      <arg column="MSISDN" javaType="java.lang.String" jdbcType="VARCHAR" />
      <arg column="SETYPE" javaType="java.lang.String" jdbcType="VARCHAR" />
      <arg column="MNOID" javaType="java.lang.String" jdbcType="VARCHAR" />
      <arg column="ACTIVATIONCODE" javaType="java.lang.String" jdbcType="VARCHAR" />
      <arg column="C2PIN" javaType="java.lang.String" jdbcType="VARCHAR" />
      <arg column="RESPONSECODE" javaType="java.lang.String" jdbcType="VARCHAR" />
      <arg column="SIR" javaType="java.lang.String" jdbcType="VARCHAR" />
      <arg column="SERVICESTAT" javaType="java.lang.Short" jdbcType="DECIMAL" />
      <arg column="ISONLINE" javaType="java.lang.String" jdbcType="CHAR" />
    </constructor>
  </resultMap>
  <sql id="Base_Column_List">
    <!--
      WARNING - @mbg.generated
      This element is automatically generated by MyBatis Generator, do not modify.
    -->
    CARDNO, ACTNO, CARD_SEQ, PRODTYPE, CARDKIND, CARDTYPE, ISPRINTACTNO, PRINTACTNO, 
    MAKEDATE, IDNO1, IDNO2, PIDNO1, PIDERR, PIDNAT, TCARD, LETTER, APPKIND, BIRTHDAY, 
    OFFSET, STATUS, PRESTATUS, APDATE, APPLY_EJFNO, BUSINO, DEPID, EMPNO, CNAME, COMPANY, 
    DEPNAME, APBRNO, TERMID, APUSERID, SIGNID, ICPU, APPGP, SELF, APPTFR, PRINT_PASS, 
    BRNO, CHIPID, SIGNDATE, PRINTDATE, EMERGENCY, UPDATE_USERID, UPDATE_TIME, CREDITNO, 
    DEBITNO, EASYNO, CUPNO, CREDITEXDATE, DEBITEXDATE, EASYEXDATE, CUPEXDATE, EASYCHIPID, 
    ISAMCHIPSEQNO, ISAMBATCHNO, ISAMMAKESEQNO, MAKECARDRESULT, MAKECARDREMARK, MAKECARDTYPE, 
    SALEMARK, MAKECARDRESDATE, SEID, PAYMENTSCHEME, MSISDN, SETYPE, MNOID, ACTIVATIONCODE, 
    C2PIN, RESPONSECODE, SIR, SERVICESTAT, ISONLINE
  </sql>
  <select id="selectByPrimaryKey" parameterType="java.lang.String" resultMap="BaseResultMap">
    <!--
      WARNING - @mbg.generated
      This element is automatically generated by MyBatis Generator, do not modify.
    -->
    select 
    <include refid="Base_Column_List" />
    from CARDNOTSM
    where CARDNO = #{cardno,jdbcType=CHAR}
  </select>
  <delete id="deleteByPrimaryKey" parameterType="com.syscom.fep.mybatis.model.Cardnotsm">
    <!--
      WARNING - @mbg.generated
      This element is automatically generated by MyBatis Generator, do not modify.
    -->
    delete from CARDNOTSM
    where CARDNO = #{cardno,jdbcType=CHAR}
  </delete>
  <insert id="insert" parameterType="com.syscom.fep.mybatis.model.Cardnotsm">
    <!--
      WARNING - @mbg.generated
      This element is automatically generated by MyBatis Generator, do not modify.
    -->
    insert into CARDNOTSM (CARDNO, ACTNO, CARD_SEQ, 
      PRODTYPE, CARDKIND, CARDTYPE, 
      ISPRINTACTNO, PRINTACTNO, MAKEDATE, 
      IDNO1, IDNO2, PIDNO1, PIDERR, 
      PIDNAT, TCARD, LETTER, APPKIND, 
      BIRTHDAY, OFFSET, STATUS, 
      PRESTATUS, APDATE, APPLY_EJFNO, 
      BUSINO, DEPID, EMPNO, 
      CNAME, COMPANY, DEPNAME, 
      APBRNO, TERMID, APUSERID, SIGNID, 
      ICPU, APPGP, SELF, APPTFR, 
      PRINT_PASS, BRNO, CHIPID, 
      SIGNDATE, PRINTDATE, EMERGENCY, 
      UPDATE_USERID, UPDATE_TIME, CREDITNO, 
      DEBITNO, EASYNO, CUPNO, 
      CREDITEXDATE, DEBITEXDATE, EASYEXDATE, 
      CUPEXDATE, EASYCHIPID, ISAMCHIPSEQNO, 
      ISAMBATCHNO, ISAMMAKESEQNO, MAKECARDRESULT, 
      MAKECARDREMARK, MAKECARDTYPE, SALEMARK, 
      MAKECARDRESDATE, SEID, PAYMENTSCHEME, 
      MSISDN, SETYPE, MNOID, 
      ACTIVATIONCODE, C2PIN, RESPONSECODE, 
      SIR, SERVICESTAT, ISONLINE
      )
    values (#{cardno,jdbcType=CHAR}, #{actno,jdbcType=CHAR}, #{cardSeq,jdbcType=DECIMAL}, 
      #{prodtype,jdbcType=DECIMAL}, #{cardkind,jdbcType=DECIMAL}, #{cardtype,jdbcType=DECIMAL}, 
      #{isprintactno,jdbcType=SMALLINT}, #{printactno,jdbcType=VARCHAR}, #{makedate,jdbcType=CHAR}, 
      #{idno1,jdbcType=CHAR}, #{idno2,jdbcType=CHAR}, #{pidno1,jdbcType=VARCHAR}, #{piderr,jdbcType=CHAR}, 
      #{pidnat,jdbcType=CHAR}, #{tcard,jdbcType=DECIMAL}, #{letter,jdbcType=CHAR}, #{appkind,jdbcType=DECIMAL}, 
      #{birthday,jdbcType=VARCHAR}, #{offset,jdbcType=INTEGER}, #{status,jdbcType=DECIMAL}, 
      #{prestatus,jdbcType=DECIMAL}, #{apdate,jdbcType=CHAR}, #{applyEjfno,jdbcType=INTEGER}, 
      #{busino,jdbcType=VARCHAR}, #{depid,jdbcType=CHAR}, #{empno,jdbcType=VARCHAR}, 
      #{cname,jdbcType=VARCHAR}, #{company,jdbcType=VARCHAR}, #{depname,jdbcType=VARCHAR}, 
      #{apbrno,jdbcType=CHAR}, #{termid,jdbcType=CHAR}, #{apuserid,jdbcType=CHAR}, #{signid,jdbcType=CHAR}, 
      #{icpu,jdbcType=DECIMAL}, #{appgp,jdbcType=CHAR}, #{self,jdbcType=CHAR}, #{apptfr,jdbcType=DECIMAL}, 
      #{printPass,jdbcType=DECIMAL}, #{brno,jdbcType=CHAR}, #{chipid,jdbcType=CHAR}, 
      #{signdate,jdbcType=CHAR}, #{printdate,jdbcType=CHAR}, #{emergency,jdbcType=SMALLINT}, 
      #{updateUserid,jdbcType=INTEGER}, #{updateTime,jdbcType=TIMESTAMP}, #{creditno,jdbcType=VARCHAR}, 
      #{debitno,jdbcType=VARCHAR}, #{easyno,jdbcType=VARCHAR}, #{cupno,jdbcType=VARCHAR}, 
      #{creditexdate,jdbcType=VARCHAR}, #{debitexdate,jdbcType=VARCHAR}, #{easyexdate,jdbcType=VARCHAR}, 
      #{cupexdate,jdbcType=VARCHAR}, #{easychipid,jdbcType=VARCHAR}, #{isamchipseqno,jdbcType=VARCHAR}, 
      #{isambatchno,jdbcType=VARCHAR}, #{isammakeseqno,jdbcType=VARCHAR}, #{makecardresult,jdbcType=VARCHAR}, 
      #{makecardremark,jdbcType=VARCHAR}, #{makecardtype,jdbcType=VARCHAR}, #{salemark,jdbcType=VARCHAR}, 
      #{makecardresdate,jdbcType=VARCHAR}, #{seid,jdbcType=VARCHAR}, #{paymentscheme,jdbcType=VARCHAR}, 
      #{msisdn,jdbcType=VARCHAR}, #{setype,jdbcType=VARCHAR}, #{mnoid,jdbcType=VARCHAR}, 
      #{activationcode,jdbcType=VARCHAR}, #{c2pin,jdbcType=VARCHAR}, #{responsecode,jdbcType=VARCHAR}, 
      #{sir,jdbcType=VARCHAR}, #{servicestat,jdbcType=DECIMAL}, #{isonline,jdbcType=CHAR}
      )
  </insert>
  <insert id="insertSelective" parameterType="com.syscom.fep.mybatis.model.Cardnotsm">
    <!--
      WARNING - @mbg.generated
      This element is automatically generated by MyBatis Generator, do not modify.
    -->
    insert into CARDNOTSM
    <trim prefix="(" suffix=")" suffixOverrides=",">
      <if test="cardno != null">
        CARDNO,
      </if>
      <if test="actno != null">
        ACTNO,
      </if>
      <if test="cardSeq != null">
        CARD_SEQ,
      </if>
      <if test="prodtype != null">
        PRODTYPE,
      </if>
      <if test="cardkind != null">
        CARDKIND,
      </if>
      <if test="cardtype != null">
        CARDTYPE,
      </if>
      <if test="isprintactno != null">
        ISPRINTACTNO,
      </if>
      <if test="printactno != null">
        PRINTACTNO,
      </if>
      <if test="makedate != null">
        MAKEDATE,
      </if>
      <if test="idno1 != null">
        IDNO1,
      </if>
      <if test="idno2 != null">
        IDNO2,
      </if>
      <if test="pidno1 != null">
        PIDNO1,
      </if>
      <if test="piderr != null">
        PIDERR,
      </if>
      <if test="pidnat != null">
        PIDNAT,
      </if>
      <if test="tcard != null">
        TCARD,
      </if>
      <if test="letter != null">
        LETTER,
      </if>
      <if test="appkind != null">
        APPKIND,
      </if>
      <if test="birthday != null">
        BIRTHDAY,
      </if>
      <if test="offset != null">
        OFFSET,
      </if>
      <if test="status != null">
        STATUS,
      </if>
      <if test="prestatus != null">
        PRESTATUS,
      </if>
      <if test="apdate != null">
        APDATE,
      </if>
      <if test="applyEjfno != null">
        APPLY_EJFNO,
      </if>
      <if test="busino != null">
        BUSINO,
      </if>
      <if test="depid != null">
        DEPID,
      </if>
      <if test="empno != null">
        EMPNO,
      </if>
      <if test="cname != null">
        CNAME,
      </if>
      <if test="company != null">
        COMPANY,
      </if>
      <if test="depname != null">
        DEPNAME,
      </if>
      <if test="apbrno != null">
        APBRNO,
      </if>
      <if test="termid != null">
        TERMID,
      </if>
      <if test="apuserid != null">
        APUSERID,
      </if>
      <if test="signid != null">
        SIGNID,
      </if>
      <if test="icpu != null">
        ICPU,
      </if>
      <if test="appgp != null">
        APPGP,
      </if>
      <if test="self != null">
        SELF,
      </if>
      <if test="apptfr != null">
        APPTFR,
      </if>
      <if test="printPass != null">
        PRINT_PASS,
      </if>
      <if test="brno != null">
        BRNO,
      </if>
      <if test="chipid != null">
        CHIPID,
      </if>
      <if test="signdate != null">
        SIGNDATE,
      </if>
      <if test="printdate != null">
        PRINTDATE,
      </if>
      <if test="emergency != null">
        EMERGENCY,
      </if>
      <if test="updateUserid != null">
        UPDATE_USERID,
      </if>
      <if test="updateTime != null">
        UPDATE_TIME,
      </if>
      <if test="creditno != null">
        CREDITNO,
      </if>
      <if test="debitno != null">
        DEBITNO,
      </if>
      <if test="easyno != null">
        EASYNO,
      </if>
      <if test="cupno != null">
        CUPNO,
      </if>
      <if test="creditexdate != null">
        CREDITEXDATE,
      </if>
      <if test="debitexdate != null">
        DEBITEXDATE,
      </if>
      <if test="easyexdate != null">
        EASYEXDATE,
      </if>
      <if test="cupexdate != null">
        CUPEXDATE,
      </if>
      <if test="easychipid != null">
        EASYCHIPID,
      </if>
      <if test="isamchipseqno != null">
        ISAMCHIPSEQNO,
      </if>
      <if test="isambatchno != null">
        ISAMBATCHNO,
      </if>
      <if test="isammakeseqno != null">
        ISAMMAKESEQNO,
      </if>
      <if test="makecardresult != null">
        MAKECARDRESULT,
      </if>
      <if test="makecardremark != null">
        MAKECARDREMARK,
      </if>
      <if test="makecardtype != null">
        MAKECARDTYPE,
      </if>
      <if test="salemark != null">
        SALEMARK,
      </if>
      <if test="makecardresdate != null">
        MAKECARDRESDATE,
      </if>
      <if test="seid != null">
        SEID,
      </if>
      <if test="paymentscheme != null">
        PAYMENTSCHEME,
      </if>
      <if test="msisdn != null">
        MSISDN,
      </if>
      <if test="setype != null">
        SETYPE,
      </if>
      <if test="mnoid != null">
        MNOID,
      </if>
      <if test="activationcode != null">
        ACTIVATIONCODE,
      </if>
      <if test="c2pin != null">
        C2PIN,
      </if>
      <if test="responsecode != null">
        RESPONSECODE,
      </if>
      <if test="sir != null">
        SIR,
      </if>
      <if test="servicestat != null">
        SERVICESTAT,
      </if>
      <if test="isonline != null">
        ISONLINE,
      </if>
    </trim>
    <trim prefix="values (" suffix=")" suffixOverrides=",">
      <if test="cardno != null">
        #{cardno,jdbcType=CHAR},
      </if>
      <if test="actno != null">
        #{actno,jdbcType=CHAR},
      </if>
      <if test="cardSeq != null">
        #{cardSeq,jdbcType=DECIMAL},
      </if>
      <if test="prodtype != null">
        #{prodtype,jdbcType=DECIMAL},
      </if>
      <if test="cardkind != null">
        #{cardkind,jdbcType=DECIMAL},
      </if>
      <if test="cardtype != null">
        #{cardtype,jdbcType=DECIMAL},
      </if>
      <if test="isprintactno != null">
        #{isprintactno,jdbcType=SMALLINT},
      </if>
      <if test="printactno != null">
        #{printactno,jdbcType=VARCHAR},
      </if>
      <if test="makedate != null">
        #{makedate,jdbcType=CHAR},
      </if>
      <if test="idno1 != null">
        #{idno1,jdbcType=CHAR},
      </if>
      <if test="idno2 != null">
        #{idno2,jdbcType=CHAR},
      </if>
      <if test="pidno1 != null">
        #{pidno1,jdbcType=VARCHAR},
      </if>
      <if test="piderr != null">
        #{piderr,jdbcType=CHAR},
      </if>
      <if test="pidnat != null">
        #{pidnat,jdbcType=CHAR},
      </if>
      <if test="tcard != null">
        #{tcard,jdbcType=DECIMAL},
      </if>
      <if test="letter != null">
        #{letter,jdbcType=CHAR},
      </if>
      <if test="appkind != null">
        #{appkind,jdbcType=DECIMAL},
      </if>
      <if test="birthday != null">
        #{birthday,jdbcType=VARCHAR},
      </if>
      <if test="offset != null">
        #{offset,jdbcType=INTEGER},
      </if>
      <if test="status != null">
        #{status,jdbcType=DECIMAL},
      </if>
      <if test="prestatus != null">
        #{prestatus,jdbcType=DECIMAL},
      </if>
      <if test="apdate != null">
        #{apdate,jdbcType=CHAR},
      </if>
      <if test="applyEjfno != null">
        #{applyEjfno,jdbcType=INTEGER},
      </if>
      <if test="busino != null">
        #{busino,jdbcType=VARCHAR},
      </if>
      <if test="depid != null">
        #{depid,jdbcType=CHAR},
      </if>
      <if test="empno != null">
        #{empno,jdbcType=VARCHAR},
      </if>
      <if test="cname != null">
        #{cname,jdbcType=VARCHAR},
      </if>
      <if test="company != null">
        #{company,jdbcType=VARCHAR},
      </if>
      <if test="depname != null">
        #{depname,jdbcType=VARCHAR},
      </if>
      <if test="apbrno != null">
        #{apbrno,jdbcType=CHAR},
      </if>
      <if test="termid != null">
        #{termid,jdbcType=CHAR},
      </if>
      <if test="apuserid != null">
        #{apuserid,jdbcType=CHAR},
      </if>
      <if test="signid != null">
        #{signid,jdbcType=CHAR},
      </if>
      <if test="icpu != null">
        #{icpu,jdbcType=DECIMAL},
      </if>
      <if test="appgp != null">
        #{appgp,jdbcType=CHAR},
      </if>
      <if test="self != null">
        #{self,jdbcType=CHAR},
      </if>
      <if test="apptfr != null">
        #{apptfr,jdbcType=DECIMAL},
      </if>
      <if test="printPass != null">
        #{printPass,jdbcType=DECIMAL},
      </if>
      <if test="brno != null">
        #{brno,jdbcType=CHAR},
      </if>
      <if test="chipid != null">
        #{chipid,jdbcType=CHAR},
      </if>
      <if test="signdate != null">
        #{signdate,jdbcType=CHAR},
      </if>
      <if test="printdate != null">
        #{printdate,jdbcType=CHAR},
      </if>
      <if test="emergency != null">
        #{emergency,jdbcType=SMALLINT},
      </if>
      <if test="updateUserid != null">
        #{updateUserid,jdbcType=INTEGER},
      </if>
      <if test="updateTime != null">
        #{updateTime,jdbcType=TIMESTAMP},
      </if>
      <if test="creditno != null">
        #{creditno,jdbcType=VARCHAR},
      </if>
      <if test="debitno != null">
        #{debitno,jdbcType=VARCHAR},
      </if>
      <if test="easyno != null">
        #{easyno,jdbcType=VARCHAR},
      </if>
      <if test="cupno != null">
        #{cupno,jdbcType=VARCHAR},
      </if>
      <if test="creditexdate != null">
        #{creditexdate,jdbcType=VARCHAR},
      </if>
      <if test="debitexdate != null">
        #{debitexdate,jdbcType=VARCHAR},
      </if>
      <if test="easyexdate != null">
        #{easyexdate,jdbcType=VARCHAR},
      </if>
      <if test="cupexdate != null">
        #{cupexdate,jdbcType=VARCHAR},
      </if>
      <if test="easychipid != null">
        #{easychipid,jdbcType=VARCHAR},
      </if>
      <if test="isamchipseqno != null">
        #{isamchipseqno,jdbcType=VARCHAR},
      </if>
      <if test="isambatchno != null">
        #{isambatchno,jdbcType=VARCHAR},
      </if>
      <if test="isammakeseqno != null">
        #{isammakeseqno,jdbcType=VARCHAR},
      </if>
      <if test="makecardresult != null">
        #{makecardresult,jdbcType=VARCHAR},
      </if>
      <if test="makecardremark != null">
        #{makecardremark,jdbcType=VARCHAR},
      </if>
      <if test="makecardtype != null">
        #{makecardtype,jdbcType=VARCHAR},
      </if>
      <if test="salemark != null">
        #{salemark,jdbcType=VARCHAR},
      </if>
      <if test="makecardresdate != null">
        #{makecardresdate,jdbcType=VARCHAR},
      </if>
      <if test="seid != null">
        #{seid,jdbcType=VARCHAR},
      </if>
      <if test="paymentscheme != null">
        #{paymentscheme,jdbcType=VARCHAR},
      </if>
      <if test="msisdn != null">
        #{msisdn,jdbcType=VARCHAR},
      </if>
      <if test="setype != null">
        #{setype,jdbcType=VARCHAR},
      </if>
      <if test="mnoid != null">
        #{mnoid,jdbcType=VARCHAR},
      </if>
      <if test="activationcode != null">
        #{activationcode,jdbcType=VARCHAR},
      </if>
      <if test="c2pin != null">
        #{c2pin,jdbcType=VARCHAR},
      </if>
      <if test="responsecode != null">
        #{responsecode,jdbcType=VARCHAR},
      </if>
      <if test="sir != null">
        #{sir,jdbcType=VARCHAR},
      </if>
      <if test="servicestat != null">
        #{servicestat,jdbcType=DECIMAL},
      </if>
      <if test="isonline != null">
        #{isonline,jdbcType=CHAR},
      </if>
    </trim>
  </insert>
  <update id="updateByPrimaryKeySelective" parameterType="com.syscom.fep.mybatis.model.Cardnotsm">
    <!--
      WARNING - @mbg.generated
      This element is automatically generated by MyBatis Generator, do not modify.
    -->
    update CARDNOTSM
    <set>
      <if test="actno != null">
        ACTNO = #{actno,jdbcType=CHAR},
      </if>
      <if test="cardSeq != null">
        CARD_SEQ = #{cardSeq,jdbcType=DECIMAL},
      </if>
      <if test="prodtype != null">
        PRODTYPE = #{prodtype,jdbcType=DECIMAL},
      </if>
      <if test="cardkind != null">
        CARDKIND = #{cardkind,jdbcType=DECIMAL},
      </if>
      <if test="cardtype != null">
        CARDTYPE = #{cardtype,jdbcType=DECIMAL},
      </if>
      <if test="isprintactno != null">
        ISPRINTACTNO = #{isprintactno,jdbcType=SMALLINT},
      </if>
      <if test="printactno != null">
        PRINTACTNO = #{printactno,jdbcType=VARCHAR},
      </if>
      <if test="makedate != null">
        MAKEDATE = #{makedate,jdbcType=CHAR},
      </if>
      <if test="idno1 != null">
        IDNO1 = #{idno1,jdbcType=CHAR},
      </if>
      <if test="idno2 != null">
        IDNO2 = #{idno2,jdbcType=CHAR},
      </if>
      <if test="pidno1 != null">
        PIDNO1 = #{pidno1,jdbcType=VARCHAR},
      </if>
      <if test="piderr != null">
        PIDERR = #{piderr,jdbcType=CHAR},
      </if>
      <if test="pidnat != null">
        PIDNAT = #{pidnat,jdbcType=CHAR},
      </if>
      <if test="tcard != null">
        TCARD = #{tcard,jdbcType=DECIMAL},
      </if>
      <if test="letter != null">
        LETTER = #{letter,jdbcType=CHAR},
      </if>
      <if test="appkind != null">
        APPKIND = #{appkind,jdbcType=DECIMAL},
      </if>
      <if test="birthday != null">
        BIRTHDAY = #{birthday,jdbcType=VARCHAR},
      </if>
      <if test="offset != null">
        OFFSET = #{offset,jdbcType=INTEGER},
      </if>
      <if test="status != null">
        STATUS = #{status,jdbcType=DECIMAL},
      </if>
      <if test="prestatus != null">
        PRESTATUS = #{prestatus,jdbcType=DECIMAL},
      </if>
      <if test="apdate != null">
        APDATE = #{apdate,jdbcType=CHAR},
      </if>
      <if test="applyEjfno != null">
        APPLY_EJFNO = #{applyEjfno,jdbcType=INTEGER},
      </if>
      <if test="busino != null">
        BUSINO = #{busino,jdbcType=VARCHAR},
      </if>
      <if test="depid != null">
        DEPID = #{depid,jdbcType=CHAR},
      </if>
      <if test="empno != null">
        EMPNO = #{empno,jdbcType=VARCHAR},
      </if>
      <if test="cname != null">
        CNAME = #{cname,jdbcType=VARCHAR},
      </if>
      <if test="company != null">
        COMPANY = #{company,jdbcType=VARCHAR},
      </if>
      <if test="depname != null">
        DEPNAME = #{depname,jdbcType=VARCHAR},
      </if>
      <if test="apbrno != null">
        APBRNO = #{apbrno,jdbcType=CHAR},
      </if>
      <if test="termid != null">
        TERMID = #{termid,jdbcType=CHAR},
      </if>
      <if test="apuserid != null">
        APUSERID = #{apuserid,jdbcType=CHAR},
      </if>
      <if test="signid != null">
        SIGNID = #{signid,jdbcType=CHAR},
      </if>
      <if test="icpu != null">
        ICPU = #{icpu,jdbcType=DECIMAL},
      </if>
      <if test="appgp != null">
        APPGP = #{appgp,jdbcType=CHAR},
      </if>
      <if test="self != null">
        SELF = #{self,jdbcType=CHAR},
      </if>
      <if test="apptfr != null">
        APPTFR = #{apptfr,jdbcType=DECIMAL},
      </if>
      <if test="printPass != null">
        PRINT_PASS = #{printPass,jdbcType=DECIMAL},
      </if>
      <if test="brno != null">
        BRNO = #{brno,jdbcType=CHAR},
      </if>
      <if test="chipid != null">
        CHIPID = #{chipid,jdbcType=CHAR},
      </if>
      <if test="signdate != null">
        SIGNDATE = #{signdate,jdbcType=CHAR},
      </if>
      <if test="printdate != null">
        PRINTDATE = #{printdate,jdbcType=CHAR},
      </if>
      <if test="emergency != null">
        EMERGENCY = #{emergency,jdbcType=SMALLINT},
      </if>
      <if test="updateUserid != null">
        UPDATE_USERID = #{updateUserid,jdbcType=INTEGER},
      </if>
      <if test="updateTime != null">
        UPDATE_TIME = #{updateTime,jdbcType=TIMESTAMP},
      </if>
      <if test="creditno != null">
        CREDITNO = #{creditno,jdbcType=VARCHAR},
      </if>
      <if test="debitno != null">
        DEBITNO = #{debitno,jdbcType=VARCHAR},
      </if>
      <if test="easyno != null">
        EASYNO = #{easyno,jdbcType=VARCHAR},
      </if>
      <if test="cupno != null">
        CUPNO = #{cupno,jdbcType=VARCHAR},
      </if>
      <if test="creditexdate != null">
        CREDITEXDATE = #{creditexdate,jdbcType=VARCHAR},
      </if>
      <if test="debitexdate != null">
        DEBITEXDATE = #{debitexdate,jdbcType=VARCHAR},
      </if>
      <if test="easyexdate != null">
        EASYEXDATE = #{easyexdate,jdbcType=VARCHAR},
      </if>
      <if test="cupexdate != null">
        CUPEXDATE = #{cupexdate,jdbcType=VARCHAR},
      </if>
      <if test="easychipid != null">
        EASYCHIPID = #{easychipid,jdbcType=VARCHAR},
      </if>
      <if test="isamchipseqno != null">
        ISAMCHIPSEQNO = #{isamchipseqno,jdbcType=VARCHAR},
      </if>
      <if test="isambatchno != null">
        ISAMBATCHNO = #{isambatchno,jdbcType=VARCHAR},
      </if>
      <if test="isammakeseqno != null">
        ISAMMAKESEQNO = #{isammakeseqno,jdbcType=VARCHAR},
      </if>
      <if test="makecardresult != null">
        MAKECARDRESULT = #{makecardresult,jdbcType=VARCHAR},
      </if>
      <if test="makecardremark != null">
        MAKECARDREMARK = #{makecardremark,jdbcType=VARCHAR},
      </if>
      <if test="makecardtype != null">
        MAKECARDTYPE = #{makecardtype,jdbcType=VARCHAR},
      </if>
      <if test="salemark != null">
        SALEMARK = #{salemark,jdbcType=VARCHAR},
      </if>
      <if test="makecardresdate != null">
        MAKECARDRESDATE = #{makecardresdate,jdbcType=VARCHAR},
      </if>
      <if test="seid != null">
        SEID = #{seid,jdbcType=VARCHAR},
      </if>
      <if test="paymentscheme != null">
        PAYMENTSCHEME = #{paymentscheme,jdbcType=VARCHAR},
      </if>
      <if test="msisdn != null">
        MSISDN = #{msisdn,jdbcType=VARCHAR},
      </if>
      <if test="setype != null">
        SETYPE = #{setype,jdbcType=VARCHAR},
      </if>
      <if test="mnoid != null">
        MNOID = #{mnoid,jdbcType=VARCHAR},
      </if>
      <if test="activationcode != null">
        ACTIVATIONCODE = #{activationcode,jdbcType=VARCHAR},
      </if>
      <if test="c2pin != null">
        C2PIN = #{c2pin,jdbcType=VARCHAR},
      </if>
      <if test="responsecode != null">
        RESPONSECODE = #{responsecode,jdbcType=VARCHAR},
      </if>
      <if test="sir != null">
        SIR = #{sir,jdbcType=VARCHAR},
      </if>
      <if test="servicestat != null">
        SERVICESTAT = #{servicestat,jdbcType=DECIMAL},
      </if>
      <if test="isonline != null">
        ISONLINE = #{isonline,jdbcType=CHAR},
      </if>
    </set>
    where CARDNO = #{cardno,jdbcType=CHAR}
  </update>
  <update id="updateByPrimaryKey" parameterType="com.syscom.fep.mybatis.model.Cardnotsm">
    <!--
      WARNING - @mbg.generated
      This element is automatically generated by MyBatis Generator, do not modify.
    -->
    update CARDNOTSM
    set ACTNO = #{actno,jdbcType=CHAR},
      CARD_SEQ = #{cardSeq,jdbcType=DECIMAL},
      PRODTYPE = #{prodtype,jdbcType=DECIMAL},
      CARDKIND = #{cardkind,jdbcType=DECIMAL},
      CARDTYPE = #{cardtype,jdbcType=DECIMAL},
      ISPRINTACTNO = #{isprintactno,jdbcType=SMALLINT},
      PRINTACTNO = #{printactno,jdbcType=VARCHAR},
      MAKEDATE = #{makedate,jdbcType=CHAR},
      IDNO1 = #{idno1,jdbcType=CHAR},
      IDNO2 = #{idno2,jdbcType=CHAR},
      PIDNO1 = #{pidno1,jdbcType=VARCHAR},
      PIDERR = #{piderr,jdbcType=CHAR},
      PIDNAT = #{pidnat,jdbcType=CHAR},
      TCARD = #{tcard,jdbcType=DECIMAL},
      LETTER = #{letter,jdbcType=CHAR},
      APPKIND = #{appkind,jdbcType=DECIMAL},
      BIRTHDAY = #{birthday,jdbcType=VARCHAR},
      OFFSET = #{offset,jdbcType=INTEGER},
      STATUS = #{status,jdbcType=DECIMAL},
      PRESTATUS = #{prestatus,jdbcType=DECIMAL},
      APDATE = #{apdate,jdbcType=CHAR},
      APPLY_EJFNO = #{applyEjfno,jdbcType=INTEGER},
      BUSINO = #{busino,jdbcType=VARCHAR},
      DEPID = #{depid,jdbcType=CHAR},
      EMPNO = #{empno,jdbcType=VARCHAR},
      CNAME = #{cname,jdbcType=VARCHAR},
      COMPANY = #{company,jdbcType=VARCHAR},
      DEPNAME = #{depname,jdbcType=VARCHAR},
      APBRNO = #{apbrno,jdbcType=CHAR},
      TERMID = #{termid,jdbcType=CHAR},
      APUSERID = #{apuserid,jdbcType=CHAR},
      SIGNID = #{signid,jdbcType=CHAR},
      ICPU = #{icpu,jdbcType=DECIMAL},
      APPGP = #{appgp,jdbcType=CHAR},
      SELF = #{self,jdbcType=CHAR},
      APPTFR = #{apptfr,jdbcType=DECIMAL},
      PRINT_PASS = #{printPass,jdbcType=DECIMAL},
      BRNO = #{brno,jdbcType=CHAR},
      CHIPID = #{chipid,jdbcType=CHAR},
      SIGNDATE = #{signdate,jdbcType=CHAR},
      PRINTDATE = #{printdate,jdbcType=CHAR},
      EMERGENCY = #{emergency,jdbcType=SMALLINT},
      UPDATE_USERID = #{updateUserid,jdbcType=INTEGER},
      UPDATE_TIME = #{updateTime,jdbcType=TIMESTAMP},
      CREDITNO = #{creditno,jdbcType=VARCHAR},
      DEBITNO = #{debitno,jdbcType=VARCHAR},
      EASYNO = #{easyno,jdbcType=VARCHAR},
      CUPNO = #{cupno,jdbcType=VARCHAR},
      CREDITEXDATE = #{creditexdate,jdbcType=VARCHAR},
      DEBITEXDATE = #{debitexdate,jdbcType=VARCHAR},
      EASYEXDATE = #{easyexdate,jdbcType=VARCHAR},
      CUPEXDATE = #{cupexdate,jdbcType=VARCHAR},
      EASYCHIPID = #{easychipid,jdbcType=VARCHAR},
      ISAMCHIPSEQNO = #{isamchipseqno,jdbcType=VARCHAR},
      ISAMBATCHNO = #{isambatchno,jdbcType=VARCHAR},
      ISAMMAKESEQNO = #{isammakeseqno,jdbcType=VARCHAR},
      MAKECARDRESULT = #{makecardresult,jdbcType=VARCHAR},
      MAKECARDREMARK = #{makecardremark,jdbcType=VARCHAR},
      MAKECARDTYPE = #{makecardtype,jdbcType=VARCHAR},
      SALEMARK = #{salemark,jdbcType=VARCHAR},
      MAKECARDRESDATE = #{makecardresdate,jdbcType=VARCHAR},
      SEID = #{seid,jdbcType=VARCHAR},
      PAYMENTSCHEME = #{paymentscheme,jdbcType=VARCHAR},
      MSISDN = #{msisdn,jdbcType=VARCHAR},
      SETYPE = #{setype,jdbcType=VARCHAR},
      MNOID = #{mnoid,jdbcType=VARCHAR},
      ACTIVATIONCODE = #{activationcode,jdbcType=VARCHAR},
      C2PIN = #{c2pin,jdbcType=VARCHAR},
      RESPONSECODE = #{responsecode,jdbcType=VARCHAR},
      SIR = #{sir,jdbcType=VARCHAR},
      SERVICESTAT = #{servicestat,jdbcType=DECIMAL},
      ISONLINE = #{isonline,jdbcType=CHAR}
    where CARDNO = #{cardno,jdbcType=CHAR}
  </update>
</mapper>