<?xml version="1.0" encoding="UTF-8"?>
<!DOCTYPE mapper PUBLIC "-//mybatis.org//DTD Mapper 3.0//EN" "http://mybatis.org/dtd/mybatis-3-mapper.dtd">
<mapper namespace="com.syscom.fep.mybatis.mapper.CorpaysumMapper">
  <resultMap id="BaseResultMap" type="com.syscom.fep.mybatis.model.Corpaysum">
    <!--
      WARNING - @mbg.generated
      This element is automatically generated by MyBatis Generator, do not modify.
    -->
    <constructor>
      <idArg column="TX_DATE" javaType="java.lang.String" jdbcType="CHAR" />
      <idArg column="TRIN_ACTNO_ACTUAL" javaType="java.lang.String" jdbcType="CHAR" />
      <idArg column="ATMNO" javaType="java.lang.String" jdbcType="VARCHAR" />
      <arg column="TOTCNT" javaType="java.lang.Integer" jdbcType="INTEGER" />
      <arg column="TOTAMT" javaType="java.math.BigDecimal" jdbcType="DECIMAL" />
      <arg column="CASHAMT" javaType="java.math.BigDecimal" jdbcType="DECIMAL" />
      <arg column="COINCNT" javaType="java.lang.Integer" jdbcType="INTEGER" />
      <arg column="COINAMT" javaType="java.math.BigDecimal" jdbcType="DECIMAL" />
      <arg column="UPDATE_USERID" javaType="java.lang.Integer" jdbcType="INTEGER" />
      <arg column="UPDATE_TIME" javaType="java.util.Date" jdbcType="TIMESTAMP" />
      <arg column="DEPOSITOR" javaType="java.lang.String" jdbcType="VARCHAR" />
    </constructor>
  </resultMap>
  <sql id="Base_Column_List">
    <!--
      WARNING - @mbg.generated
      This element is automatically generated by MyBatis Generator, do not modify.
    -->
    TX_DATE, TRIN_ACTNO_ACTUAL, ATMNO, TOTCNT, TOTAMT, CASHAMT, COINCNT, COINAMT, UPDATE_USERID, 
    UPDATE_TIME, DEPOSITOR
  </sql>
  <select id="selectByPrimaryKey" parameterType="map" resultMap="BaseResultMap">
    <!--
      WARNING - @mbg.generated
      This element is automatically generated by MyBatis Generator, do not modify.
    -->
    select 
    <include refid="Base_Column_List" />
    from CORPAYSUM
    where TX_DATE = #{txDate,jdbcType=CHAR}
      and TRIN_ACTNO_ACTUAL = #{trinActnoActual,jdbcType=CHAR}
      and ATMNO = #{atmno,jdbcType=VARCHAR}
  </select>
  <delete id="deleteByPrimaryKey" parameterType="com.syscom.fep.mybatis.model.Corpaysum">
    <!--
      WARNING - @mbg.generated
      This element is automatically generated by MyBatis Generator, do not modify.
    -->
    delete from CORPAYSUM
    where TX_DATE = #{txDate,jdbcType=CHAR}
      and TRIN_ACTNO_ACTUAL = #{trinActnoActual,jdbcType=CHAR}
      and ATMNO = #{atmno,jdbcType=VARCHAR}
  </delete>
  <insert id="insert" parameterType="com.syscom.fep.mybatis.model.Corpaysum">
    <!--
      WARNING - @mbg.generated
      This element is automatically generated by MyBatis Generator, do not modify.
    -->
    insert into CORPAYSUM (TX_DATE, TRIN_ACTNO_ACTUAL, ATMNO, 
      TOTCNT, TOTAMT, CASHAMT, 
      COINCNT, COINAMT, UPDATE_USERID, 
      UPDATE_TIME, DEPOSITOR)
    values (#{txDate,jdbcType=CHAR}, #{trinActnoActual,jdbcType=CHAR}, #{atmno,jdbcType=VARCHAR}, 
      #{totcnt,jdbcType=INTEGER}, #{totamt,jdbcType=DECIMAL}, #{cashamt,jdbcType=DECIMAL}, 
      #{coincnt,jdbcType=INTEGER}, #{coinamt,jdbcType=DECIMAL}, #{updateUserid,jdbcType=INTEGER}, 
      #{updateTime,jdbcType=TIMESTAMP}, #{depositor,jdbcType=VARCHAR})
  </insert>
  <insert id="insertSelective" parameterType="com.syscom.fep.mybatis.model.Corpaysum">
    <!--
      WARNING - @mbg.generated
      This element is automatically generated by MyBatis Generator, do not modify.
    -->
    insert into CORPAYSUM
    <trim prefix="(" suffix=")" suffixOverrides=",">
      <if test="txDate != null">
        TX_DATE,
      </if>
      <if test="trinActnoActual != null">
        TRIN_ACTNO_ACTUAL,
      </if>
      <if test="atmno != null">
        ATMNO,
      </if>
      <if test="totcnt != null">
        TOTCNT,
      </if>
      <if test="totamt != null">
        TOTAMT,
      </if>
      <if test="cashamt != null">
        CASHAMT,
      </if>
      <if test="coincnt != null">
        COINCNT,
      </if>
      <if test="coinamt != null">
        COINAMT,
      </if>
      <if test="updateUserid != null">
        UPDATE_USERID,
      </if>
      <if test="updateTime != null">
        UPDATE_TIME,
      </if>
      <if test="depositor != null">
        DEPOSITOR,
      </if>
    </trim>
    <trim prefix="values (" suffix=")" suffixOverrides=",">
      <if test="txDate != null">
        #{txDate,jdbcType=CHAR},
      </if>
      <if test="trinActnoActual != null">
        #{trinActnoActual,jdbcType=CHAR},
      </if>
      <if test="atmno != null">
        #{atmno,jdbcType=VARCHAR},
      </if>
      <if test="totcnt != null">
        #{totcnt,jdbcType=INTEGER},
      </if>
      <if test="totamt != null">
        #{totamt,jdbcType=DECIMAL},
      </if>
      <if test="cashamt != null">
        #{cashamt,jdbcType=DECIMAL},
      </if>
      <if test="coincnt != null">
        #{coincnt,jdbcType=INTEGER},
      </if>
      <if test="coinamt != null">
        #{coinamt,jdbcType=DECIMAL},
      </if>
      <if test="updateUserid != null">
        #{updateUserid,jdbcType=INTEGER},
      </if>
      <if test="updateTime != null">
        #{updateTime,jdbcType=TIMESTAMP},
      </if>
      <if test="depositor != null">
        #{depositor,jdbcType=VARCHAR},
      </if>
    </trim>
  </insert>
  <update id="updateByPrimaryKeySelective" parameterType="com.syscom.fep.mybatis.model.Corpaysum">
    <!--
      WARNING - @mbg.generated
      This element is automatically generated by MyBatis Generator, do not modify.
    -->
    update CORPAYSUM
    <set>
      <if test="totcnt != null">
        TOTCNT = #{totcnt,jdbcType=INTEGER},
      </if>
      <if test="totamt != null">
        TOTAMT = #{totamt,jdbcType=DECIMAL},
      </if>
      <if test="cashamt != null">
        CASHAMT = #{cashamt,jdbcType=DECIMAL},
      </if>
      <if test="coincnt != null">
        COINCNT = #{coincnt,jdbcType=INTEGER},
      </if>
      <if test="coinamt != null">
        COINAMT = #{coinamt,jdbcType=DECIMAL},
      </if>
      <if test="updateUserid != null">
        UPDATE_USERID = #{updateUserid,jdbcType=INTEGER},
      </if>
      <if test="updateTime != null">
        UPDATE_TIME = #{updateTime,jdbcType=TIMESTAMP},
      </if>
      <if test="depositor != null">
        DEPOSITOR = #{depositor,jdbcType=VARCHAR},
      </if>
    </set>
    where TX_DATE = #{txDate,jdbcType=CHAR}
      and TRIN_ACTNO_ACTUAL = #{trinActnoActual,jdbcType=CHAR}
      and ATMNO = #{atmno,jdbcType=VARCHAR}
  </update>
  <update id="updateByPrimaryKey" parameterType="com.syscom.fep.mybatis.model.Corpaysum">
    <!--
      WARNING - @mbg.generated
      This element is automatically generated by MyBatis Generator, do not modify.
    -->
    update CORPAYSUM
    set TOTCNT = #{totcnt,jdbcType=INTEGER},
      TOTAMT = #{totamt,jdbcType=DECIMAL},
      CASHAMT = #{cashamt,jdbcType=DECIMAL},
      COINCNT = #{coincnt,jdbcType=INTEGER},
      COINAMT = #{coinamt,jdbcType=DECIMAL},
      UPDATE_USERID = #{updateUserid,jdbcType=INTEGER},
      UPDATE_TIME = #{updateTime,jdbcType=TIMESTAMP},
      DEPOSITOR = #{depositor,jdbcType=VARCHAR}
    where TX_DATE = #{txDate,jdbcType=CHAR}
      and TRIN_ACTNO_ACTUAL = #{trinActnoActual,jdbcType=CHAR}
      and ATMNO = #{atmno,jdbcType=VARCHAR}
  </update>
</mapper>